{
    "HorizonLayout": [
        {
            "layout": "logo",
            "image": "https://trello.com/1/cards/688191e140a035bb2a31245a/attachments/6883497a460c2eab8ce273f3/download/Usaha_Untuk__HARTABADI.png",
            "showMenu": true,
            "showLogo": true,
            "showSearch": true,
            "showCart": false,
            "showNotification": true,
            "showBadgeCart": false,
            "opacity": 1.0,
            "iconOpacity": 0.0,
            "iconRadius": 6.0,
            "iconSpreadRadius": 0.0,
            "iconSize": 24.0,
            "logoSize": 50.0
        },
        {
            "items": [
                {
                    "name": "",
                    "image": "https://trello.com/1/cards/5f8fe6093cd3ef24d9ede5f5/attachments/5f8fe62076ec8884a587b043/previews/5f8fe62176ec8884a587b05c/download/Mobile_Template_1b.png",
                    "padding": 15,
                    "category": 29
                },
                {
                    "image": "https://user-images.githubusercontent.com/1459805/59846818-12672e80-938b-11e9-8184-5f7bfe66f1a2.png",
                    "padding": 15,
                    "category": 28
                },
                {
                    "image": "https://user-images.githubusercontent.com/1459805/60091808-a19b8a00-976f-11e9-9cc7-576ca05c2442.png",
                    "padding": 15,
                    "product": 30
                }
            ],
            "design": "default",
            "layout": "bannerImage",
            "radius": 2,
            "autoPlay": false,
            "isSlider": true,
            "showNumber": false,
            "showBackGround": true
        },
        {
            "fit": "fitWidth",
            "items": [
                {
                    "image": "https://trello.com/1/cards/5fb8de4a9ffe12204a2a3607/attachments/5fb8de57d9356e0af474cc94/previews/5fb8de58d9356e0af474cca0/download/image.png",
                    "coupon": "blackf",
                    "radius": 9,
                    "padding": 15
                }
            ],
            "design": "static",
            "height": 0.15,
            "layout": "bannerImage",
            "marginTop": 20,
            "marginLeft": 0,
            "marginRight": 0,
            "marginBottom": 0
        },
        {
            "name": "Our Blog Posts",
            "layout": "blog"
        }
    ],
    "Setting": {
        "ShowChat": true,
        "MainColor": "#3FC1BE",
        "FontFamily": "Roboto",
        "FontHeader": "Raleway",
        "StickyHeader": true,
        "ProductListLayout": "list"
    },
    "TabBar": [
        {
            "key": "hBiXpAEJdC",
            "icon": "https://uup.hartabadi.id/wp-content/uploads/2025/07/008-home-xquare.png",
            "layout": "home",
            "defaultTab": false,
            "fullscreen": false,
            "showOriginalColor": false
        },
        {
            "key": "bidwMgKHShs",
            "url": "https://uup.hartabadi.id/cf-listing-page/",
            "icon": "https://uup.hartabadi.id/wp-content/uploads/2025/07/004-crowdfunding-1.png",
            "label": "UUP",
            "title": "UUP",
            "layout": "page",
            "defaultTab": false,
            "fullscreen": false,
            "showOriginalColor": false
        },
        {
            "key": "cpTrZklpXjXOJ",
            "url": "https://uup.hartabadi.id/portal/",
            "auth": true,
            "icon": "https://uup.hartabadi.id/wp-content/uploads/2025/07/015-group-users.png",
            "title": "Community",
            "layout": "page",
            "defaultTab": false,
            "fullscreen": false,
            "showOriginalColor": false
        },
        {
            "key": "BozgEVxgHJSgVQ",
            "icon": "https://uup.hartabadi.id/wp-content/uploads/2025/07/012-user-profile.png",
            "layout": "profile",
            "defaultTab": false,
            "fullscreen": false,
            "showBackground": true,
            "showOriginalColor": false
        }
    ],
    "AppBar": null,
    "Drawer": {
        "logo": "https://uup.hartabadi.id/wp-content/uploads/2025/07/cropped-Usaha-Untuk-HARTABADI.png",
        "items": [
            {
                "show": true,
                "type": "home"
            },
            {
                "show": true,
                "type": "blog"
            },
            {
                "show": true,
                "type": "categories"
            },
            {
                "show": true,
                "type": "cart"
            },
            {
                "show": true,
                "type": "profile"
            },
            {
                "show": true,
                "type": "login"
            },
            {
                "show": false,
                "type": "category"
            }
        ],
        "enable": true,
        "filter": 0,
        "logoDark": null,
        "safeArea": false,
        "iconColor": null,
        "textColor": null,
        "logoConfig": {
            "boxFit": "cover",
            "height": 38,
            "marginTop": 60,
            "marginLeft": 5,
            "marginRight": 0,
            "marginBottom": 10
        },
        "zoomConfig": null,
        "colorFilter": null,
        "subDrawerItem": {},
        "backgroundColor": null,
        "backgroundImage": null
    }
}